openapi_dto_gen/__init__.py
openapi_dto_gen/cli.py
openapi_dto_gen-0.2.0.dist-info/licenses/LICENSE
openapi_dto_gen-0.2.0.dist-info/METADATA
openapi_dto_gen-0.2.0.dist-info/WHEEL
openapi_dto_gen-0.2.0.dist-info/entry_points.txt
openapi_dto_gen-0.2.0.dist-info/top_level.txt
openapi_dto_gen-0.2.0.dist-info/RECORD
