Metadata-Version: 2.4
Name: openapi-dto-gen
Version: 0.2.0
Summary: Generate Java DTOs from OpenAPI/Swagger components.schemas.
Author-email: Generated by ChatGPT <noreply@example.com>
License: MIT License
Keywords: openapi,swagger,dto,java,codegen
Classifier: Programming Language :: Python :: 3
Classifier: License :: OSI Approved :: MIT License
Classifier: Operating System :: OS Independent
Classifier: Topic :: Software Development :: Code Generators
Requires-Python: >=3.8
License-File: LICENSE
Requires-Dist: pyyaml<7,>=6
Dynamic: license-file
